haxballgym_tools/examples/sb3_multi_example.py
haxballgym_tools/examples/sb3_single_example.py
haxballgym_tools/model_testing/play_model_1s.py
haxballgym_tools/model_testing/test_reward.py
haxballgym_tools/sb3_utils/__init__.py
haxballgym_tools/sb3_utils/sb3_hax_multiple_instance.py
haxballgym_tools/sb3_utils/sb3_hax_single_instance.py
haxballgym_tools-1.1.1.dist-info/METADATA
haxballgym_tools-1.1.1.dist-info/WHEEL
haxballgym_tools-1.1.1.dist-info/RECORD
